{
  "artist": "Maxine Vee",
  "ink": "Emerald",
  "ink_cost": 2,
  "inkable": true,
  "name": "Strike A Good Match",
  "rarity": "Common",
  "number": 96,
  "keywords": [],
  "flavor_text": "Please bring honor to us\nPlease bring honor to us all",
  "types": [
    "Action",
    "Song"
  ],
  "set": {
    "key": "ink",
    "name": "Into the Inklands",
    "number": 3
  },
  "text": "(A character with cost X or more can {e} to sing this song for free.)\n\nDraw 2 cards, then choose and discard a card."
}
