{
    "artist": "Anh Dang",
    "ink": "Ruby",
    "ink_cost": 3,
    "inkable": false,
    "name": "Peter Pan",
    "types": [
        "Character"
    ],
    "rarity": "Common",
    "number": 119,
    "keywords": [
        "Rush"
    ],
    "flavor_text": "\"Nobody calls Pan a coward and lives! I'll fight you man-to-man, with one hand behind my back.\"",
    "text": "Rush (This character can challenge the turn they're played.) ",
    "classifications": [
        "Storyborn",
        "Hero"
    ],
    "version": "Fearless Fighter",
    "willpower": 2,
    "strength": 3,
    "lore": 1,
    "set": {
        "key": "TFC",
        "name": "The First Chapter",
        "number": 1
    }
}